<?xml version='1.0' encoding='UTF-8'?>
<faces-config version="2.2"
              xmlns="http://xmlns.jcp.org/xml/ns/javaee"
              xmlns:xsi="http://www.w3.org/2001/XMLSchema-instance"
              xsi:schemaLocation="http://xmlns.jcp.org/xml/ns/javaee http://xmlns.jcp.org/xml/ns/javaee/web-facesconfig_2_2.xsd">
    <navigation-rule>        
        <navigation-case>
            <from-outcome>inicio</from-outcome>
            <to-view-id>/vistas/inicio.xhtml</to-view-id>
            <redirect />
        </navigation-case>               
        
        <navignavigation-case>
            <from-outcome>servicio</from-outcome>
            <to-view-id>vistas/servicio.xhtml</to-view-id>
            <redirect />
        </navignavigation-case>
        
        <navignavigation-case>
            <from-outcome>seguridad</from-outcome>
            <to-view-id>vistas/seguridad.xhtml</to-view-id>
            <redirect />
        </navignavigation-case>
    </navigation-rule>
</faces-config>
